{
  "company_id": "abridge",
  "company_name": "Abridge",
  "source_homepage": "https://www.abridge.com",
  "crawled_at": "2025-12-13T23:05:05Z",
  "run_type": "full-load",
  "output_dir": "/Users/charmydarji/Desktop/invest-iq/data/raw/abridge/initial",
  "content_sha256": "099dc56880eca7c91cce718291860fdbfc5d5d22b5041d838a69683e4a85fd9c",
  "content_length": 471877,
  "parser": "lab1_scraper",
  "version": 1,
  "scraper_result": {
    "company_id": "abridge",
    "company_name": "Abridge",
    "manifest_path": "/Users/charmydarji/Desktop/invest-iq/data/raw/abridge/initial/manifest.json",
    "sections": {
      "homepage": "https://www.abridge.com",
      "about": "https://www.abridge.com/about",
      "product": "https://www.abridge.com/product",
      "careers": "https://www.abridge.com/about#careers",
      "blog": "https://www.abridge.com/blog"
    },
    "status": "success"
  }
}