{
  "company_id": "figure",
  "company_name": "Figure",
  "source_homepage": "https://www.figure.com",
  "crawled_at": "2025-12-13T23:34:38Z",
  "run_type": "full-load",
  "output_dir": "/Users/charmydarji/Desktop/invest-iq/data/raw/figure/initial",
  "content_sha256": "aa1fe75842f375bc54c2e04ff764cea0e3bca0a1a95e07dff80b78d4ba23bc9e",
  "content_length": 41251677,
  "parser": "lab1_scraper",
  "version": 1,
  "scraper_result": {
    "company_id": "figure",
    "company_name": "Figure",
    "manifest_path": "/Users/charmydarji/Desktop/invest-iq/data/raw/figure/initial/manifest.json",
    "sections": {
      "homepage": "https://www.figure.com",
      "about": "https://www.figure.com/about",
      "product": "https://www.figure.com/home-equity-line",
      "careers": "https://www.figure.com/careers",
      "blog": "https://www.figure.com/blog"
    },
    "status": "success"
  }
}